CHANGELOG.rst
CONTRIBUTORS.txt
LICENSE.txt
MANIFEST.in
README.rst
setup.cfg
setup.py
docs/Makefile
docs/requirements.txt
docs/source/changelog.rst
docs/source/conf.py
docs/source/design.rst
docs/source/forms.rst
docs/source/getstarted.rst
docs/source/index.rst
docs/source/javascript.rst
docs/source/validation.rst
docs/source/widget.rst
tests/test.html
tests/test_commands.py
tests/test_deep.txt
tests/test_hierarchy.py
tests/test_i18n.py
tests/test_js.py
tests/test_mako_util.py
tests/test_middleware.py
tests/test_misc.py
tests/test_params.py
tests/test_resources.py
tests/test_template.py
tests/test_validation.py
tests/test_validators.txt
tests/test_vdwidget.txt
tests/test_widgets.py
tests/test_widgets.txt
tests/testapi.py
tests/htmlcov/index.html
tests/htmlcov/tw2_core.html
tests/htmlcov/tw2_core_command.html
tests/htmlcov/tw2_core_compat.html
tests/htmlcov/tw2_core_core.html
tests/htmlcov/tw2_core_i18n.html
tests/htmlcov/tw2_core_jinja_util.html
tests/htmlcov/tw2_core_js.html
tests/htmlcov/tw2_core_mako_util.html
tests/htmlcov/tw2_core_middleware.html
tests/htmlcov/tw2_core_params.html
tests/htmlcov/tw2_core_resources.html
tests/htmlcov/tw2_core_templates.html
tests/htmlcov/tw2_core_templating.html
tests/htmlcov/tw2_core_util.html
tests/htmlcov/tw2_core_validation.html
tests/htmlcov/tw2_core_widgets.html
tw2/__init__.py
tw2.core.egg-info/PKG-INFO
tw2.core.egg-info/SOURCES.txt
tw2.core.egg-info/dependency_links.txt
tw2.core.egg-info/entry_points.txt
tw2.core.egg-info/namespace_packages.txt
tw2.core.egg-info/not-zip-safe
tw2.core.egg-info/pbr.json
tw2.core.egg-info/requires.txt
tw2.core.egg-info/top_level.txt
tw2/core/__init__.py
tw2/core/command.py
tw2/core/compat.py
tw2/core/core.py
tw2/core/i18n.py
tw2/core/jinja_util.py
tw2/core/js.py
tw2/core/jsonify.py
tw2/core/mako_util.py
tw2/core/middleware.py
tw2/core/params.py
tw2/core/resources.py
tw2/core/templating.py
tw2/core/util.py
tw2/core/validation.py
tw2/core/widgets.py
tw2/core/i18n/de/LC_MESSAGES/tw2core.mo
tw2/core/i18n/en/LC_MESSAGES/tw2core.mo
tw2/core/i18n/es/LC_MESSAGES/tw2core.mo
tw2/core/i18n/fr/LC_MESSAGES/tw2core.mo
tw2/core/i18n/it/LC_MESSAGES/tw2core.mo
tw2/core/i18n/nl/LC_MESSAGES/tw2core.mo
tw2/core/i18n/ru/LC_MESSAGES/tw2core.mo
tw2/core/i18n/uk/LC_MESSAGES/tw2core.mo
